<?xml version="1.0"?>
<annotation>
    <filename>000007089.tif</filename>
    <source>
        <annotation>ESRI ArcGIS Pro</annotation>
    </source>
    <size>
        <width>128</width>
        <height>128</height>
        <depth>4</depth>
    </size>
    <object>
        <name>1</name>
        <bndbox>
            <xmin>93.21</xmin>
            <ymin>75.22</ymin>
            <xmax>109.21</xmax>
            <ymax>87.93</ymax>
        </bndbox>
    </object>
    <object>
        <name>1</name>
        <bndbox>
            <xmin>85.36</xmin>
            <ymin>98.12</ymin>
            <xmax>99.73</xmax>
            <ymax>108.89</ymax>
        </bndbox>
    </object>
    <object>
        <name>1</name>
        <bndbox>
            <xmin>96.15</xmin>
            <ymin>94.96</ymin>
            <xmax>106.57</xmax>
            <ymax>104.34</ymax>
        </bndbox>
    </object>
</annotation>
